README.md
setup.cfg
setup.py
SalavatiHolidayCheckup/HolidayCheck.py
SalavatiHolidayCheckup/__init__.py
holiday_checkup.egg-info/PKG-INFO
holiday_checkup.egg-info/SOURCES.txt
holiday_checkup.egg-info/dependency_links.txt
holiday_checkup.egg-info/requires.txt
holiday_checkup.egg-info/top_level.txt